{
  "audit_date": "2026-04-06",
  "generated_at": "2026-04-07T10:18:18",
  "counts": {
    "freeze_matches": 69,
    "api_found": 69,
    "finished_matches": 68,
    "analyzed_rows": 68,
    "skipped_not_finished": 1,
    "skipped_no_result": 0
  },
  "stats": {
    "PTGG": {
      "total": 45,
      "hit": 6,
      "rate": 13.33
    },
    "PTO15": {
      "total": 36,
      "hit": 12,
      "rate": 33.33
    },
    "OVER": {
      "total": 65,
      "hit": 28,
      "rate": 43.08
    },
    "STRONG_OVER": {
      "total": 57,
      "hit": 26,
      "rate": 45.61
    },
    "BOOST": {
      "total": 20,
      "hit": 4,
      "rate": 20.0
    },
    "GOLD": {
      "total": 8,
      "hit": 2,
      "rate": 25.0
    },
    "FISH_GG": {
      "total": 0,
      "hit": 0,
      "rate": 0.0
    },
    "FISH_OVER": {
      "total": 0,
      "hit": 0,
      "rate": 0.0
    }
  },
  "settlement_rules": {
    "PTGG": "HT entrambe segnano",
    "PTO15": "HT almeno 2 gol",
    "OVER": "FT almeno 3 gol",
    "STRONG_OVER": "FT almeno 3 gol",
    "BOOST": "PTO15 + OVER",
    "GOLD": "BOOST proxy",
    "FISH_GG": "FT entrambe segnano",
    "FISH_OVER": "FT almeno 3 gol"
  }
}